ctimed_rotating_file_handler/__init__.py
ctimed_rotating_file_handler/ctimed_rotating_file_handler.py
ctimed_rotating_file_handler-0.1.2.dist-info/LICENSE
ctimed_rotating_file_handler-0.1.2.dist-info/METADATA
ctimed_rotating_file_handler-0.1.2.dist-info/WHEEL
ctimed_rotating_file_handler-0.1.2.dist-info/top_level.txt
ctimed_rotating_file_handler-0.1.2.dist-info/RECORD
