Metadata-Version: 2.1
Name: ctimed-rotating-file-handler
Version: 0.1.2
Summary: TimedRotatingFileHandler using ctime instead of mtime to determine rollover times.
Author-email: Silmaril <python@silmaril.de>
License: This is free and unencumbered software released into the public domain.        
Project-URL: Homepage, https://codeberg.org/silmaril/CTimedRotatingFileHandler
Project-URL: Bug Tracker, https://codeberg.org/silmaril/CTimedRotatingFileHandler/issues
Keywords: logging,filetime
Classifier: Development Status :: 5 - Production/Stable
Classifier: Programming Language :: Python :: 3
Classifier: License :: OSI Approved :: The Unlicense (Unlicense)
Classifier: Operating System :: OS Independent
Classifier: Intended Audience :: Developers
Classifier: Topic :: System :: Logging
Requires-Python: >=3.9
License-File: LICENSE
Requires-Dist: win32-setctime (==1.1.0) ; platform_system == "Windows"
